setup.py
my_package/__init__.py
my_package/module1.py
wzh123_package.egg-info/PKG-INFO
wzh123_package.egg-info/SOURCES.txt
wzh123_package.egg-info/dependency_links.txt
wzh123_package.egg-info/not-zip-safe
wzh123_package.egg-info/top_level.txt