Metadata-Version: 1.0
Name: wzh123-package
Version: 0.1
Summary: clinical trial information retriver
Home-page: UNKNOWN
Author: wangzehan
Author-email: 2287359887@qq.com
License: MIT
Platform: UNKNOWN
